log_colors/__init__.py
log_colors/log_colors.py
log_colors-0.1.1.dist-info/METADATA
log_colors-0.1.1.dist-info/WHEEL
log_colors-0.1.1.dist-info/top_level.txt
log_colors-0.1.1.dist-info/RECORD
