Metadata-Version: 2.4
Name: log_colors
Version: 0.1.1
Summary: A colorful logging library for Python
Home-page: https://github.com/avery-kb/log_colors
Author: avery-kb
Classifier: Programming Language :: Python :: 3
Classifier: Operating System :: OS Independent
Requires-Python: >=3.7
Dynamic: author
Dynamic: classifier
Dynamic: description
Dynamic: description-content-type
Dynamic: home-page
Dynamic: requires-python
Dynamic: summary
